{
  "chunk_id": "chunk::srd_35::epicfeats::156_tenacious_magic_epic",
  "document_id": "srd_35::epicfeats::156_tenacious_magic_epic",
  "source_ref": {
    "source_id": "srd_35",
    "title": "System Reference Document",
    "edition": "3.5e",
    "source_type": "srd",
    "authority_level": "official_reference"
  },
  "locator": {
    "section_path": [
      "EpicFeats",
      "TENACIOUS MAGIC [EPIC]"
    ],
    "source_location": "EpicFeats.rtf#156_tenacious_magic_epic"
  },
  "chunk_type": "subsection",
  "content": "Prerequisites: Spellcraft 15 ranks.\nBenefit: Choose one spell the character knows or spell-like ability the character possesses. Whenever the chosen form of magic would otherwise end due to a dispel effect, the magic is instead only suppressed for 1d4 rounds. The magic still ends when its duration expires, but the suppressed rounds do not count against its duration. The character can dismiss his or her own spell or spell-like ability (if dismissible) or dispel his or her own tenacious magic normally.\nSpecial: A character can gain this feat multiple times. Each time he or she takes the feat, it applies to a different spell or spell-like ability.",
  "chunk_version": "v1-section-passthrough",
  "previous_chunk_id": "chunk::srd_35::epicfeats::155_terrifying_rage_epic",
  "next_chunk_id": "chunk::srd_35::epicfeats::157_thundering_rage_epic"
}
