{
  "chunk_id": "chunk::srd_35::powerlist::008_6th_level_psion_wilder_powers",
  "document_id": "srd_35::powerlist::008_6th_level_psion_wilder_powers",
  "source_ref": {
    "source_id": "srd_35",
    "title": "System Reference Document",
    "edition": "3.5e",
    "source_type": "srd",
    "authority_level": "official_reference"
  },
  "locator": {
    "section_path": [
      "PowerList",
      "6TH-LEVEL PSION/WILDER POWERS"
    ],
    "source_location": "PowerList.rtf#008_6th_level_psion_wilder_powers"
  },
  "chunk_type": "subsection",
  "content": "Aura AlterationA: Repairs psyche or makes subject seem to be something it is not.\nBreath of the Black DragonA: Breathe acid for 11d6 damage.\nCloud Mind, Mass: Erase knowledge of your presence from the minds of one creature/level.\nContingency, PsionicX: Sets trigger condition for another power.\nCo-opt Concentration: Take control of foe's concentration power.\nDisintegrate, PsionicA: Turn one creature or object to dust.\nFuse FleshA: Fuse subject's flesh, creating a helpless mass.\nOverland Flight, Psionic: You fly at a speed of 40 ft. and can hustle over long distances.\nRemote View Trap: Deal 8d6 points electricity damage to those who seek to view you at a distance.\nRetrieveA: Teleport to your hand an item you can see.\nSuspend Life: Put yourself in a state akin to suspended animation.\nTemporal AccelerationA: Your time frame accelerates for 1 round.",
  "chunk_version": "v1-section-passthrough",
  "previous_chunk_id": "chunk::srd_35::powerlist::007_5th_level_psion_wilder_powers",
  "next_chunk_id": "chunk::srd_35::powerlist::009_7th_level_psion_wilder_powers"
}
