{
  "chunk_id": "chunk::srd_35::psionicpowersq_w::076_display_visual",
  "document_id": "srd_35::psionicpowersq_w::076_display_visual",
  "source_ref": {
    "source_id": "srd_35",
    "title": "System Reference Document",
    "edition": "3.5e",
    "source_type": "srd",
    "authority_level": "official_reference"
  },
  "locator": {
    "section_path": [
      "PsionicPowersQ-W",
      "Display: Visual"
    ],
    "source_location": "PsionicPowersQ-W.rtf#076_display_visual"
  },
  "chunk_type": "subsection",
  "content": "Manifesting Time: 1 standard action\nRange: Close (25 ft. + 5 ft./2 levels)\nArea: Spread with a radius of 25 ft. + 5 ft./2 levels, centered on you",
  "chunk_version": "v1-section-passthrough",
  "previous_chunk_id": "chunk::srd_35::psionicpowersq_w::075_power_points_9",
  "next_chunk_id": "chunk::srd_35::psionicpowersq_w::077_power_points_7"
}
